[
  {
    "sport": "nba",
    "date_time": "04/19/2026 01:00 PM",
    "team1": "Philadelphia 76ers (45-37)",
    "team2": "Boston Celtics (56-26)",
    "team1_win_pct": "20.8%",
    "team2_win_pct": "79.2%",
    "team1_moneyline": "+600",
    "team2_moneyline": "-800",
    "team1_spread": "+12\u00bd-109",
    "team2_spread": "-12\u00bd-109",
    "proj_score_1": "101.9",
    "proj_score_2": "110.7",
    "total": "212.6",
    "over_line": "o213\u00bd-110",
    "under_line": "u213\u00bd-110",
    "score1": "",
    "score2": "",
    "game_status": ""
  },
  {
    "sport": "nba",
    "date_time": "04/19/2026 03:30 PM",
    "team1": "Phoenix Suns (45-37)",
    "team2": "Oklahoma City Thunder (64-18)",
    "team1_win_pct": "14.5%",
    "team2_win_pct": "85.5%",
    "team1_moneyline": "+800",
    "team2_moneyline": "-1200",
    "team1_spread": "+14\u00bd-110",
    "team2_spread": "-14-109",
    "proj_score_1": "98.1",
    "proj_score_2": "109.1",
    "total": "207.2",
    "over_line": "o215\u00bd-110",
    "under_line": "u215\u00bd-110",
    "score1": "",
    "score2": "",
    "game_status": ""
  },
  {
    "sport": "nba",
    "date_time": "04/19/2026 09:00 PM",
    "team1": "Portland Trail Blazers (42-40)",
    "team2": "San Antonio Spurs (62-20)",
    "team1_win_pct": "21.1%",
    "team2_win_pct": "78.9%",
    "team1_moneyline": "+475",
    "team2_moneyline": "-550",
    "team1_spread": "+11-109",
    "team2_spread": "-11-109",
    "proj_score_1": "106.3",
    "proj_score_2": "114.9",
    "total": "221.2",
    "over_line": "o220\u00bd-110",
    "under_line": "u222\u00bd-110",
    "score1": "",
    "score2": "",
    "game_status": ""
  },
  {
    "sport": "nba",
    "date_time": "04/18/2026 08:35 PM",
    "team1": "Houston Rockets",
    "team2": "Los Angeles Lakers",
    "team1_win_pct": "61.3%",
    "team2_win_pct": "38.7%",
    "team1_moneyline": "-140",
    "team2_moneyline": "+125",
    "team1_spread": "-2\u00bd-109",
    "team2_spread": "+2\u00bd-105",
    "proj_score_1": "",
    "proj_score_2": "",
    "total": "",
    "over_line": "",
    "under_line": "",
    "score1": "98",
    "score2": "107",
    "game_status": ""
  },
  {
    "sport": "nba",
    "date_time": "04/18/2026 06:15 PM",
    "team1": "Atlanta Hawks",
    "team2": "New York Knicks",
    "team1_win_pct": "37.0%",
    "team2_win_pct": "63.0%",
    "team1_moneyline": "+210",
    "team2_moneyline": "-240",
    "team1_spread": "+6\u00bd-115",
    "team2_spread": "-6-109",
    "proj_score_1": "",
    "proj_score_2": "",
    "total": "",
    "over_line": "",
    "under_line": "",
    "score1": "102",
    "score2": "113",
    "game_status": ""
  },
  {
    "sport": "nba",
    "date_time": "04/18/2026 03:40 PM",
    "team1": "Minnesota Timberwolves",
    "team2": "Denver Nuggets",
    "team1_win_pct": "30.0%",
    "team2_win_pct": "70.0%",
    "team1_moneyline": "+240",
    "team2_moneyline": "-280",
    "team1_spread": "+7-109",
    "team2_spread": "-7-105",
    "proj_score_1": "",
    "proj_score_2": "",
    "total": "",
    "over_line": "",
    "under_line": "",
    "score1": "105",
    "score2": "116",
    "game_status": ""
  },
  {
    "sport": "nba",
    "date_time": "04/18/2026 01:08 PM",
    "team1": "Toronto Raptors",
    "team2": "Cleveland Cavaliers",
    "team1_win_pct": "26.8%",
    "team2_win_pct": "73.2%",
    "team1_moneyline": "+320",
    "team2_moneyline": "-375",
    "team1_spread": "+8\u00bd-109",
    "team2_spread": "-8\u00bd-109",
    "proj_score_1": "",
    "proj_score_2": "",
    "total": "",
    "over_line": "",
    "under_line": "",
    "score1": "113",
    "score2": "126",
    "game_status": ""
  },
  {
    "sport": "nba",
    "date_time": "04/17/2026 10:14 PM",
    "team1": "Golden State Warriors",
    "team2": "Phoenix Suns",
    "team1_win_pct": "41.0%",
    "team2_win_pct": "59.0%",
    "team1_moneyline": "+135",
    "team2_moneyline": "-145",
    "team1_spread": "+3-109",
    "team2_spread": "-2\u00bd-115",
    "proj_score_1": "",
    "proj_score_2": "",
    "total": "",
    "over_line": "",
    "under_line": "",
    "score1": "96",
    "score2": "111",
    "game_status": ""
  },
  {
    "sport": "nba",
    "date_time": "04/17/2026 07:30 PM",
    "team1": "Charlotte Hornets",
    "team2": "Orlando Magic",
    "team1_win_pct": "59.8%",
    "team2_win_pct": "40.2%",
    "team1_moneyline": "-150",
    "team2_moneyline": "+130",
    "team1_spread": "-3-105",
    "team2_spread": "+3-109",
    "proj_score_1": "",
    "proj_score_2": "",
    "total": "",
    "over_line": "",
    "under_line": "",
    "score1": "90",
    "score2": "121",
    "game_status": ""
  },
  {
    "sport": "nba",
    "date_time": "04/15/2026 10:15 PM",
    "team1": "Golden State Warriors",
    "team2": "Los Angeles Clippers",
    "team1_win_pct": "39.4%",
    "team2_win_pct": "60.6%",
    "team1_moneyline": "+190",
    "team2_moneyline": "-200",
    "team1_spread": "+5\u00bd-109",
    "team2_spread": "-5\u00bd-105",
    "proj_score_1": "",
    "proj_score_2": "",
    "total": "",
    "over_line": "",
    "under_line": "",
    "score1": "126",
    "score2": "121",
    "game_status": ""
  },
  {
    "sport": "nba",
    "date_time": "04/15/2026 07:30 PM",
    "team1": "Orlando Magic",
    "team2": "Philadelphia 76ers",
    "team1_win_pct": "52.9%",
    "team2_win_pct": "47.1%",
    "team1_moneyline": "+105",
    "team2_moneyline": "-115",
    "team1_spread": "+1\u00bd-109",
    "team2_spread": "-1-110",
    "proj_score_1": "",
    "proj_score_2": "",
    "total": "",
    "over_line": "",
    "under_line": "",
    "score1": "97",
    "score2": "109",
    "game_status": ""
  },
  {
    "sport": "nba",
    "date_time": "04/14/2026 10:15 PM",
    "team1": "Portland Trail Blazers",
    "team2": "Phoenix Suns",
    "team1_win_pct": "43.9%",
    "team2_win_pct": "56.1%",
    "team1_moneyline": "+135",
    "team2_moneyline": "-145",
    "team1_spread": "+3-109",
    "team2_spread": "-3-105",
    "proj_score_1": "",
    "proj_score_2": "",
    "total": "",
    "over_line": "",
    "under_line": "",
    "score1": "114",
    "score2": "110",
    "game_status": ""
  },
  {
    "sport": "nba",
    "date_time": "04/14/2026 07:30 PM",
    "team1": "Miami Heat",
    "team2": "Charlotte Hornets",
    "team1_win_pct": "35.2%",
    "team2_win_pct": "64.8%",
    "team1_moneyline": "+225",
    "team2_moneyline": "-240",
    "team1_spread": "+6\u00bd-110",
    "team2_spread": "-6-109",
    "proj_score_1": "",
    "proj_score_2": "",
    "total": "",
    "over_line": "",
    "under_line": "",
    "score1": "126",
    "score2": "127",
    "game_status": ""
  },
  {
    "sport": "nba",
    "date_time": "04/12/2026 08:40 PM",
    "team1": "Utah Jazz",
    "team2": "Los Angeles Lakers",
    "team1_win_pct": "12.3%",
    "team2_win_pct": "87.7%",
    "team1_moneyline": "+775",
    "team2_moneyline": "-1100",
    "team1_spread": "+15-110",
    "team2_spread": "-14\u00bd-109",
    "proj_score_1": "",
    "proj_score_2": "",
    "total": "",
    "over_line": "",
    "under_line": "",
    "score1": "107",
    "score2": "131",
    "game_status": ""
  },
  {
    "sport": "nba",
    "date_time": "04/12/2026 08:40 PM",
    "team1": "Denver Nuggets",
    "team2": "San Antonio Spurs",
    "team1_win_pct": "33.2%",
    "team2_win_pct": "66.8%",
    "team1_moneyline": "+370",
    "team2_moneyline": "-430",
    "team1_spread": "+9\u00bd-105",
    "team2_spread": "-9\u00bd-109",
    "proj_score_1": "",
    "proj_score_2": "",
    "total": "",
    "over_line": "",
    "under_line": "",
    "score1": "128",
    "score2": "118",
    "game_status": ""
  },
  {
    "sport": "nba",
    "date_time": "04/12/2026 08:40 PM",
    "team1": "Sacramento Kings",
    "team2": "Portland Trail Blazers",
    "team1_win_pct": "10.3%",
    "team2_win_pct": "89.7%",
    "team1_moneyline": "+1300",
    "team2_moneyline": "-2200",
    "team1_spread": "+19-109",
    "team2_spread": "-19-109",
    "proj_score_1": "",
    "proj_score_2": "",
    "total": "",
    "over_line": "",
    "under_line": "",
    "score1": "110",
    "score2": "122",
    "game_status": ""
  },
  {
    "sport": "nba",
    "date_time": "04/12/2026 08:40 PM",
    "team1": "Memphis Grizzlies",
    "team2": "Houston Rockets",
    "team1_win_pct": "10.9%",
    "team2_win_pct": "89.1%",
    "team1_moneyline": "+750",
    "team2_moneyline": "-1100",
    "team1_spread": "+14\u00bd-109",
    "team2_spread": "-14\u00bd-109",
    "proj_score_1": "",
    "proj_score_2": "",
    "total": "",
    "over_line": "",
    "under_line": "",
    "score1": "101",
    "score2": "132",
    "game_status": ""
  },
  {
    "sport": "nba",
    "date_time": "04/12/2026 08:40 PM",
    "team1": "Chicago Bulls",
    "team2": "Dallas Mavericks",
    "team1_win_pct": "37.5%",
    "team2_win_pct": "62.5%",
    "team1_moneyline": "+180",
    "team2_moneyline": "-200",
    "team1_spread": "+5\u00bd-110",
    "team2_spread": "-5-109",
    "proj_score_1": "",
    "proj_score_2": "",
    "total": "",
    "over_line": "",
    "under_line": "",
    "score1": "128",
    "score2": "149",
    "game_status": ""
  },
  {
    "sport": "nba",
    "date_time": "04/12/2026 08:40 PM",
    "team1": "New Orleans Pelicans",
    "team2": "Minnesota Timberwolves",
    "team1_win_pct": "36.5%",
    "team2_win_pct": "63.5%",
    "team1_moneyline": "+160",
    "team2_moneyline": "-175",
    "team1_spread": "+4\u00bd-110",
    "team2_spread": "-4-109",
    "proj_score_1": "",
    "proj_score_2": "",
    "total": "",
    "over_line": "",
    "under_line": "",
    "score1": "126",
    "score2": "132",
    "game_status": ""
  }
]