[
  {
    "id": "644f37a134497f23c6d3821ad599b48b",
    "sport_key": "icehockey_nhl",
    "sport_title": "NHL",
    "commence_time": "2026-05-04T23:10:00Z",
    "home_team": "Carolina Hurricanes",
    "away_team": "Philadelphia Flyers",
    "bookmakers": [
      {
        "key": "draftkings",
        "title": "DraftKings",
        "last_update": "2026-05-04T10:10:44Z",
        "markets": [
          {
            "key": "h2h",
            "last_update": "2026-05-04T10:10:44Z",
            "outcomes": [
              {
                "name": "Carolina Hurricanes",
                "price": 1.39
              },
              {
                "name": "Philadelphia Flyers",
                "price": 3.1
              }
            ]
          },
          {
            "key": "spreads",
            "last_update": "2026-05-04T10:10:44Z",
            "outcomes": [
              {
                "name": "Carolina Hurricanes",
                "price": 2.1,
                "point": -1.5
              },
              {
                "name": "Philadelphia Flyers",
                "price": 1.77,
                "point": 1.5
              }
            ]
          },
          {
            "key": "totals",
            "last_update": "2026-05-04T10:10:44Z",
            "outcomes": [
              {
                "name": "Over",
                "price": 2.05,
                "point": 5.5
              },
              {
                "name": "Under",
                "price": 1.8,
                "point": 5.5
              }
            ]
          }
        ]
      }
    ]
  },
  {
    "id": "df8e2f4e8a0bfcff34d6bbd0619bc3dd",
    "sport_key": "icehockey_nhl",
    "sport_title": "NHL",
    "commence_time": "2026-05-05T01:40:18Z",
    "home_team": "Vegas Golden Knights",
    "away_team": "Anaheim Ducks",
    "bookmakers": [
      {
        "key": "draftkings",
        "title": "DraftKings",
        "last_update": "2026-05-04T10:10:44Z",
        "markets": [
          {
            "key": "h2h",
            "last_update": "2026-05-04T10:10:44Z",
            "outcomes": [
              {
                "name": "Anaheim Ducks",
                "price": 2.4
              },
              {
                "name": "Vegas Golden Knights",
                "price": 1.6
              }
            ]
          },
          {
            "key": "spreads",
            "last_update": "2026-05-04T10:10:44Z",
            "outcomes": [
              {
                "name": "Anaheim Ducks",
                "price": 1.56,
                "point": 1.5
              },
              {
                "name": "Vegas Golden Knights",
                "price": 2.5,
                "point": -1.5
              }
            ]
          },
          {
            "key": "totals",
            "last_update": "2026-05-04T10:10:44Z",
            "outcomes": [
              {
                "name": "Over",
                "price": 1.98,
                "point": 6.5
              },
              {
                "name": "Under",
                "price": 1.85,
                "point": 6.5
              }
            ]
          }
        ]
      }
    ]
  },
  {
    "id": "fbc314d1e8c60127f6b1a302f544af53",
    "sport_key": "icehockey_nhl",
    "sport_title": "NHL",
    "commence_time": "2026-05-06T00:10:08Z",
    "home_team": "Colorado Avalanche",
    "away_team": "Minnesota Wild",
    "bookmakers": [
      {
        "key": "draftkings",
        "title": "DraftKings",
        "last_update": "2026-05-04T10:10:44Z",
        "markets": [
          {
            "key": "h2h",
            "last_update": "2026-05-04T10:10:44Z",
            "outcomes": [
              {
                "name": "Colorado Avalanche",
                "price": 1.49
              },
              {
                "name": "Minnesota Wild",
                "price": 2.7
              }
            ]
          },
          {
            "key": "spreads",
            "last_update": "2026-05-04T10:10:44Z",
            "outcomes": [
              {
                "name": "Colorado Avalanche",
                "price": 2.24,
                "point": -1.5
              },
              {
                "name": "Minnesota Wild",
                "price": 1.68,
                "point": 1.5
              }
            ]
          },
          {
            "key": "totals",
            "last_update": "2026-05-04T10:10:44Z",
            "outcomes": [
              {
                "name": "Over",
                "price": 1.95,
                "point": 6.5
              },
              {
                "name": "Under",
                "price": 1.87,
                "point": 6.5
              }
            ]
          }
        ]
      }
    ]
  },
  {
    "id": "8458afd03d1b3e8305f8e6362cd8e3b7",
    "sport_key": "icehockey_nhl",
    "sport_title": "NHL",
    "commence_time": "2026-05-06T23:00:36Z",
    "home_team": "Buffalo Sabres",
    "away_team": "Montr\u00e9al Canadiens",
    "bookmakers": [
      {
        "key": "draftkings",
        "title": "DraftKings",
        "last_update": "2026-05-04T10:10:44Z",
        "markets": [
          {
            "key": "h2h",
            "last_update": "2026-05-04T10:10:44Z",
            "outcomes": [
              {
                "name": "Buffalo Sabres",
                "price": 1.74
              },
              {
                "name": "Montr\u00e9al Canadiens",
                "price": 2.14
              }
            ]
          },
          {
            "key": "spreads",
            "last_update": "2026-05-04T10:10:44Z",
            "outcomes": [
              {
                "name": "Buffalo Sabres",
                "price": 2.9,
                "point": -1.5
              },
              {
                "name": "Montr\u00e9al Canadiens",
                "price": 1.43,
                "point": 1.5
              }
            ]
          },
          {
            "key": "totals",
            "last_update": "2026-05-04T10:10:44Z",
            "outcomes": [
              {
                "name": "Over",
                "price": 1.82,
                "point": 5.5
              },
              {
                "name": "Under",
                "price": 2.02,
                "point": 5.5
              }
            ]
          }
        ]
      }
    ]
  }
]