[
  {
    "id": "8b80dbee1665ae5e68b02b12836273c5",
    "sport_key": "baseball_mlb",
    "sport_title": "MLB",
    "commence_time": "2026-05-23T17:11:00Z",
    "home_team": "Cincinnati Reds",
    "away_team": "St. Louis Cardinals",
    "bookmakers": [
      {
        "key": "draftkings",
        "title": "DraftKings",
        "last_update": "2026-05-23T09:04:52Z",
        "markets": [
          {
            "key": "h2h",
            "last_update": "2026-05-23T09:04:52Z",
            "outcomes": [
              {
                "name": "Cincinnati Reds",
                "price": 1.91
              },
              {
                "name": "St. Louis Cardinals",
                "price": 1.91
              }
            ]
          },
          {
            "key": "spreads",
            "last_update": "2026-05-23T09:04:52Z",
            "outcomes": [
              {
                "name": "Cincinnati Reds",
                "price": 1.58,
                "point": 1.5
              },
              {
                "name": "St. Louis Cardinals",
                "price": 2.42,
                "point": -1.5
              }
            ]
          },
          {
            "key": "totals",
            "last_update": "2026-05-23T09:04:52Z",
            "outcomes": [
              {
                "name": "Over",
                "price": 1.91,
                "point": 9.5
              },
              {
                "name": "Under",
                "price": 1.91,
                "point": 9.5
              }
            ]
          }
        ]
      }
    ]
  },
  {
    "id": "85a0d1f951c22b4be483d2e435fd0454",
    "sport_key": "baseball_mlb",
    "sport_title": "MLB",
    "commence_time": "2026-05-23T17:36:00Z",
    "home_team": "New York Yankees",
    "away_team": "Tampa Bay Rays",
    "bookmakers": [
      {
        "key": "draftkings",
        "title": "DraftKings",
        "last_update": "2026-05-23T09:04:52Z",
        "markets": [
          {
            "key": "h2h",
            "last_update": "2026-05-23T09:04:52Z",
            "outcomes": [
              {
                "name": "New York Yankees",
                "price": 1.7
              },
              {
                "name": "Tampa Bay Rays",
                "price": 2.19
              }
            ]
          },
          {
            "key": "spreads",
            "last_update": "2026-05-23T09:04:52Z",
            "outcomes": [
              {
                "name": "New York Yankees",
                "price": 2.59,
                "point": -1.5
              },
              {
                "name": "Tampa Bay Rays",
                "price": 1.52,
                "point": 1.5
              }
            ]
          },
          {
            "key": "totals",
            "last_update": "2026-05-23T09:04:52Z",
            "outcomes": [
              {
                "name": "Over",
                "price": 1.89,
                "point": 7.0
              },
              {
                "name": "Under",
                "price": 1.93,
                "point": 7.0
              }
            ]
          }
        ]
      }
    ]
  },
  {
    "id": "5e73a3b37ba9f2d7f8672112ad0b5d3a",
    "sport_key": "baseball_mlb",
    "sport_title": "MLB",
    "commence_time": "2026-05-23T18:21:00Z",
    "home_team": "Chicago Cubs",
    "away_team": "Houston Astros",
    "bookmakers": [
      {
        "key": "draftkings",
        "title": "DraftKings",
        "last_update": "2026-05-23T09:04:52Z",
        "markets": [
          {
            "key": "h2h",
            "last_update": "2026-05-23T09:04:52Z",
            "outcomes": [
              {
                "name": "Chicago Cubs",
                "price": 1.64
              },
              {
                "name": "Houston Astros",
                "price": 2.29
              }
            ]
          },
          {
            "key": "spreads",
            "last_update": "2026-05-23T09:04:52Z",
            "outcomes": [
              {
                "name": "Chicago Cubs",
                "price": 2.41,
                "point": -1.5
              },
              {
                "name": "Houston Astros",
                "price": 1.58,
                "point": 1.5
              }
            ]
          },
          {
            "key": "totals",
            "last_update": "2026-05-23T09:04:52Z",
            "outcomes": [
              {
                "name": "Over",
                "price": 1.97,
                "point": 7.5
              },
              {
                "name": "Under",
                "price": 1.85,
                "point": 7.5
              }
            ]
          }
        ]
      }
    ]
  },
  {
    "id": "1d419a4245a0f02f79282579190123f2",
    "sport_key": "baseball_mlb",
    "sport_title": "MLB",
    "commence_time": "2026-05-23T19:08:00Z",
    "home_team": "Toronto Blue Jays",
    "away_team": "Pittsburgh Pirates",
    "bookmakers": [
      {
        "key": "draftkings",
        "title": "DraftKings",
        "last_update": "2026-05-23T09:04:52Z",
        "markets": [
          {
            "key": "h2h",
            "last_update": "2026-05-23T09:04:52Z",
            "outcomes": [
              {
                "name": "Pittsburgh Pirates",
                "price": 1.64
              },
              {
                "name": "Toronto Blue Jays",
                "price": 2.3
              }
            ]
          },
          {
            "key": "spreads",
            "last_update": "2026-05-23T09:04:52Z",
            "outcomes": [
              {
                "name": "Pittsburgh Pirates",
                "price": 2.18,
                "point": -1.5
              },
              {
                "name": "Toronto Blue Jays",
                "price": 1.7,
                "point": 1.5
              }
            ]
          },
          {
            "key": "totals",
            "last_update": "2026-05-23T09:04:52Z",
            "outcomes": [
              {
                "name": "Over",
                "price": 1.94,
                "point": 7.5
              },
              {
                "name": "Under",
                "price": 1.88,
                "point": 7.5
              }
            ]
          }
        ]
      }
    ]
  },
  {
    "id": "71e440d0877946408af692d321e7972b",
    "sport_key": "baseball_mlb",
    "sport_title": "MLB",
    "commence_time": "2026-05-23T20:06:00Z",
    "home_team": "Baltimore Orioles",
    "away_team": "Detroit Tigers",
    "bookmakers": [
      {
        "key": "draftkings",
        "title": "DraftKings",
        "last_update": "2026-05-23T09:04:52Z",
        "markets": [
          {
            "key": "h2h",
            "last_update": "2026-05-23T09:04:52Z",
            "outcomes": [
              {
                "name": "Baltimore Orioles",
                "price": 1.83
              },
              {
                "name": "Detroit Tigers",
                "price": 1.99
              }
            ]
          },
          {
            "key": "spreads",
            "last_update": "2026-05-23T09:04:52Z",
            "outcomes": [
              {
                "name": "Baltimore Orioles",
                "price": 1.53,
                "point": 1.5
              },
              {
                "name": "Detroit Tigers",
                "price": 2.55,
                "point": -1.5
              }
            ]
          },
          {
            "key": "totals",
            "last_update": "2026-05-23T09:04:52Z",
            "outcomes": [
              {
                "name": "Over",
                "price": 1.87,
                "point": 8.0
              },
              {
                "name": "Under",
                "price": 1.96,
                "point": 8.0
              }
            ]
          }
        ]
      }
    ]
  },
  {
    "id": "d414dc60c44b7705cece8354be2575d1",
    "sport_key": "baseball_mlb",
    "sport_title": "MLB",
    "commence_time": "2026-05-23T20:06:00Z",
    "home_team": "San Francisco Giants",
    "away_team": "Chicago White Sox",
    "bookmakers": [
      {
        "key": "draftkings",
        "title": "DraftKings",
        "last_update": "2026-05-23T09:04:52Z",
        "markets": [
          {
            "key": "h2h",
            "last_update": "2026-05-23T09:04:52Z",
            "outcomes": [
              {
                "name": "Chicago White Sox",
                "price": 2.04
              },
              {
                "name": "San Francisco Giants",
                "price": 1.79
              }
            ]
          },
          {
            "key": "spreads",
            "last_update": "2026-05-23T09:04:52Z",
            "outcomes": [
              {
                "name": "Chicago White Sox",
                "price": 1.5,
                "point": 1.5
              },
              {
                "name": "San Francisco Giants",
                "price": 2.63,
                "point": -1.5
              }
            ]
          },
          {
            "key": "totals",
            "last_update": "2026-05-23T09:04:52Z",
            "outcomes": [
              {
                "name": "Over",
                "price": 1.95,
                "point": 8.5
              },
              {
                "name": "Under",
                "price": 1.88,
                "point": 8.5
              }
            ]
          }
        ]
      }
    ]
  },
  {
    "id": "bb14f988c4cc921c1b5286bf757183f6",
    "sport_key": "baseball_mlb",
    "sport_title": "MLB",
    "commence_time": "2026-05-23T20:06:00Z",
    "home_team": "Philadelphia Phillies",
    "away_team": "Cleveland Guardians",
    "bookmakers": [
      {
        "key": "draftkings",
        "title": "DraftKings",
        "last_update": "2026-05-23T09:04:52Z",
        "markets": [
          {
            "key": "h2h",
            "last_update": "2026-05-23T09:04:52Z",
            "outcomes": [
              {
                "name": "Cleveland Guardians",
                "price": 2.63
              },
              {
                "name": "Philadelphia Phillies",
                "price": 1.5
              }
            ]
          },
          {
            "key": "spreads",
            "last_update": "2026-05-23T09:04:52Z",
            "outcomes": [
              {
                "name": "Cleveland Guardians",
                "price": 1.76,
                "point": 1.5
              },
              {
                "name": "Philadelphia Phillies",
                "price": 2.09,
                "point": -1.5
              }
            ]
          },
          {
            "key": "totals",
            "last_update": "2026-05-23T09:04:52Z",
            "outcomes": [
              {
                "name": "Over",
                "price": 2.02,
                "point": 7.5
              },
              {
                "name": "Under",
                "price": 1.82,
                "point": 7.5
              }
            ]
          }
        ]
      }
    ]
  },
  {
    "id": "8d35e402aab765eeda746ea98f694dc6",
    "sport_key": "baseball_mlb",
    "sport_title": "MLB",
    "commence_time": "2026-05-23T20:11:00Z",
    "home_team": "Atlanta Braves",
    "away_team": "Washington Nationals",
    "bookmakers": [
      {
        "key": "draftkings",
        "title": "DraftKings",
        "last_update": "2026-05-23T09:04:52Z",
        "markets": [
          {
            "key": "h2h",
            "last_update": "2026-05-23T09:04:52Z",
            "outcomes": [
              {
                "name": "Atlanta Braves",
                "price": 1.51
              },
              {
                "name": "Washington Nationals",
                "price": 2.62
              }
            ]
          },
          {
            "key": "spreads",
            "last_update": "2026-05-23T09:04:52Z",
            "outcomes": [
              {
                "name": "Atlanta Braves",
                "price": 2.04,
                "point": -1.5
              },
              {
                "name": "Washington Nationals",
                "price": 1.79,
                "point": 1.5
              }
            ]
          },
          {
            "key": "totals",
            "last_update": "2026-05-23T09:04:52Z",
            "outcomes": [
              {
                "name": "Over",
                "price": 1.93,
                "point": 9.0
              },
              {
                "name": "Under",
                "price": 1.89,
                "point": 9.0
              }
            ]
          }
        ]
      }
    ]
  },
  {
    "id": "613fbf2d89b0e9cffb2d70ebdbe1f178",
    "sport_key": "baseball_mlb",
    "sport_title": "MLB",
    "commence_time": "2026-05-23T20:11:00Z",
    "home_team": "Boston Red Sox",
    "away_team": "Minnesota Twins",
    "bookmakers": [
      {
        "key": "draftkings",
        "title": "DraftKings",
        "last_update": "2026-05-23T09:04:52Z",
        "markets": [
          {
            "key": "h2h",
            "last_update": "2026-05-23T09:04:52Z",
            "outcomes": [
              {
                "name": "Boston Red Sox",
                "price": 1.85
              },
              {
                "name": "Minnesota Twins",
                "price": 1.98
              }
            ]
          },
          {
            "key": "spreads",
            "last_update": "2026-05-23T09:04:52Z",
            "outcomes": [
              {
                "name": "Boston Red Sox",
                "price": 1.52,
                "point": 1.5
              },
              {
                "name": "Minnesota Twins",
                "price": 2.59,
                "point": -1.5
              }
            ]
          },
          {
            "key": "totals",
            "last_update": "2026-05-23T09:04:52Z",
            "outcomes": [
              {
                "name": "Over",
                "price": 1.91,
                "point": 8.5
              },
              {
                "name": "Under",
                "price": 1.91,
                "point": 8.5
              }
            ]
          }
        ]
      }
    ]
  },
  {
    "id": "203ad61a573433f885122e8811cd8350",
    "sport_key": "baseball_mlb",
    "sport_title": "MLB",
    "commence_time": "2026-05-23T20:11:00Z",
    "home_team": "Kansas City Royals",
    "away_team": "Seattle Mariners",
    "bookmakers": [
      {
        "key": "draftkings",
        "title": "DraftKings",
        "last_update": "2026-05-23T09:04:52Z",
        "markets": [
          {
            "key": "h2h",
            "last_update": "2026-05-23T09:04:52Z",
            "outcomes": [
              {
                "name": "Kansas City Royals",
                "price": 2.14
              },
              {
                "name": "Seattle Mariners",
                "price": 1.73
              }
            ]
          },
          {
            "key": "spreads",
            "last_update": "2026-05-23T09:04:52Z",
            "outcomes": [
              {
                "name": "Kansas City Royals",
                "price": 1.7,
                "point": 1.5
              },
              {
                "name": "Seattle Mariners",
                "price": 2.19,
                "point": -1.5
              }
            ]
          },
          {
            "key": "totals",
            "last_update": "2026-05-23T09:04:52Z",
            "outcomes": [
              {
                "name": "Over",
                "price": 1.89,
                "point": 8.5
              },
              {
                "name": "Under",
                "price": 1.93,
                "point": 8.5
              }
            ]
          }
        ]
      }
    ]
  },
  {
    "id": "8cd9a8c51a76ba56fe6f4a174a01a9ee",
    "sport_key": "baseball_mlb",
    "sport_title": "MLB",
    "commence_time": "2026-05-23T20:11:00Z",
    "home_team": "Miami Marlins",
    "away_team": "New York Mets",
    "bookmakers": [
      {
        "key": "draftkings",
        "title": "DraftKings",
        "last_update": "2026-05-23T09:04:52Z",
        "markets": [
          {
            "key": "h2h",
            "last_update": "2026-05-23T09:04:52Z",
            "outcomes": [
              {
                "name": "Miami Marlins",
                "price": 1.87
              },
              {
                "name": "New York Mets",
                "price": 1.95
              }
            ]
          },
          {
            "key": "spreads",
            "last_update": "2026-05-23T09:04:52Z",
            "outcomes": [
              {
                "name": "Miami Marlins",
                "price": 1.54,
                "point": 1.5
              },
              {
                "name": "New York Mets",
                "price": 2.52,
                "point": -1.5
              }
            ]
          },
          {
            "key": "totals",
            "last_update": "2026-05-23T09:04:52Z",
            "outcomes": [
              {
                "name": "Over",
                "price": 1.98,
                "point": 8.0
              },
              {
                "name": "Under",
                "price": 1.85,
                "point": 8.0
              }
            ]
          }
        ]
      }
    ]
  },
  {
    "id": "188966d9ba86d03383806bac10bc777c",
    "sport_key": "baseball_mlb",
    "sport_title": "MLB",
    "commence_time": "2026-05-23T23:16:00Z",
    "home_team": "Cincinnati Reds",
    "away_team": "St. Louis Cardinals",
    "bookmakers": [
      {
        "key": "draftkings",
        "title": "DraftKings",
        "last_update": "2026-05-23T09:04:52Z",
        "markets": [
          {
            "key": "h2h",
            "last_update": "2026-05-23T09:04:52Z",
            "outcomes": [
              {
                "name": "Cincinnati Reds",
                "price": 1.93
              },
              {
                "name": "St. Louis Cardinals",
                "price": 1.89
              }
            ]
          },
          {
            "key": "spreads",
            "last_update": "2026-05-23T09:04:52Z",
            "outcomes": [
              {
                "name": "Cincinnati Reds",
                "price": 1.61,
                "point": 1.5
              },
              {
                "name": "St. Louis Cardinals",
                "price": 2.36,
                "point": -1.5
              }
            ]
          },
          {
            "key": "totals",
            "last_update": "2026-05-23T09:04:52Z",
            "outcomes": [
              {
                "name": "Over",
                "price": 1.93,
                "point": 9.5
              },
              {
                "name": "Under",
                "price": 1.89,
                "point": 9.5
              }
            ]
          }
        ]
      }
    ]
  },
  {
    "id": "e8edd4604077b2fc638f1b2e3db08545",
    "sport_key": "baseball_mlb",
    "sport_title": "MLB",
    "commence_time": "2026-05-23T23:16:00Z",
    "home_team": "Milwaukee Brewers",
    "away_team": "Los Angeles Dodgers",
    "bookmakers": [
      {
        "key": "draftkings",
        "title": "DraftKings",
        "last_update": "2026-05-23T09:04:52Z",
        "markets": [
          {
            "key": "h2h",
            "last_update": "2026-05-23T09:04:52Z",
            "outcomes": [
              {
                "name": "Los Angeles Dodgers",
                "price": 1.81
              },
              {
                "name": "Milwaukee Brewers",
                "price": 2.02
              }
            ]
          },
          {
            "key": "spreads",
            "last_update": "2026-05-23T09:04:52Z",
            "outcomes": [
              {
                "name": "Los Angeles Dodgers",
                "price": 2.29,
                "point": -1.5
              },
              {
                "name": "Milwaukee Brewers",
                "price": 1.64,
                "point": 1.5
              }
            ]
          },
          {
            "key": "totals",
            "last_update": "2026-05-23T09:04:52Z",
            "outcomes": [
              {
                "name": "Over",
                "price": 1.95,
                "point": 9.0
              },
              {
                "name": "Under",
                "price": 1.87,
                "point": 9.0
              }
            ]
          }
        ]
      }
    ]
  },
  {
    "id": "1b110a61227c86ab2f069fb32d6720af",
    "sport_key": "baseball_mlb",
    "sport_title": "MLB",
    "commence_time": "2026-05-24T01:41:00Z",
    "home_team": "San Diego Padres",
    "away_team": "Athletics",
    "bookmakers": [
      {
        "key": "draftkings",
        "title": "DraftKings",
        "last_update": "2026-05-23T09:04:52Z",
        "markets": [
          {
            "key": "h2h",
            "last_update": "2026-05-23T09:04:52Z",
            "outcomes": [
              {
                "name": "Athletics",
                "price": 1.91
              },
              {
                "name": "San Diego Padres",
                "price": 1.91
              }
            ]
          },
          {
            "key": "spreads",
            "last_update": "2026-05-23T09:04:52Z",
            "outcomes": [
              {
                "name": "Athletics",
                "price": 2.49,
                "point": -1.5
              },
              {
                "name": "San Diego Padres",
                "price": 1.55,
                "point": 1.5
              }
            ]
          },
          {
            "key": "totals",
            "last_update": "2026-05-23T09:04:52Z",
            "outcomes": [
              {
                "name": "Over",
                "price": 1.95,
                "point": 8.0
              },
              {
                "name": "Under",
                "price": 1.87,
                "point": 8.0
              }
            ]
          }
        ]
      }
    ]
  },
  {
    "id": "cdafb9b5d32150ff1e65098271c992b2",
    "sport_key": "baseball_mlb",
    "sport_title": "MLB",
    "commence_time": "2026-05-24T02:06:00Z",
    "home_team": "Los Angeles Angels",
    "away_team": "Texas Rangers",
    "bookmakers": [
      {
        "key": "draftkings",
        "title": "DraftKings",
        "last_update": "2026-05-23T09:04:52Z",
        "markets": [
          {
            "key": "h2h",
            "last_update": "2026-05-23T09:04:52Z",
            "outcomes": [
              {
                "name": "Los Angeles Angels",
                "price": 2.18
              },
              {
                "name": "Texas Rangers",
                "price": 1.7
              }
            ]
          },
          {
            "key": "spreads",
            "last_update": "2026-05-23T09:04:52Z",
            "outcomes": [
              {
                "name": "Los Angeles Angels",
                "price": 1.67,
                "point": 1.5
              },
              {
                "name": "Texas Rangers",
                "price": 2.24,
                "point": -1.5
              }
            ]
          },
          {
            "key": "totals",
            "last_update": "2026-05-23T09:04:52Z",
            "outcomes": [
              {
                "name": "Over",
                "price": 1.9,
                "point": 8.0
              },
              {
                "name": "Under",
                "price": 1.93,
                "point": 8.0
              }
            ]
          }
        ]
      }
    ]
  },
  {
    "id": "aa331215453a8e2dcfbcdcaa7cacecbe",
    "sport_key": "baseball_mlb",
    "sport_title": "MLB",
    "commence_time": "2026-05-24T02:11:00Z",
    "home_team": "Arizona Diamondbacks",
    "away_team": "Colorado Rockies",
    "bookmakers": [
      {
        "key": "draftkings",
        "title": "DraftKings",
        "last_update": "2026-05-23T09:04:52Z",
        "markets": [
          {
            "key": "h2h",
            "last_update": "2026-05-23T09:04:52Z",
            "outcomes": [
              {
                "name": "Arizona Diamondbacks",
                "price": 1.56
              },
              {
                "name": "Colorado Rockies",
                "price": 2.48
              }
            ]
          },
          {
            "key": "spreads",
            "last_update": "2026-05-23T09:04:52Z",
            "outcomes": [
              {
                "name": "Arizona Diamondbacks",
                "price": 2.19,
                "point": -1.5
              },
              {
                "name": "Colorado Rockies",
                "price": 1.69,
                "point": 1.5
              }
            ]
          },
          {
            "key": "totals",
            "last_update": "2026-05-23T09:04:52Z",
            "outcomes": [
              {
                "name": "Over",
                "price": 1.82,
                "point": 9.0
              },
              {
                "name": "Under",
                "price": 2.01,
                "point": 9.0
              }
            ]
          }
        ]
      }
    ]
  }
]