[
  {
    "id": "63302649",
    "sport_key": "baseball_mlb",
    "sport_title": "MLB",
    "commence_time": "2026-06-05T00:05:00Z",
    "home_team": "Chicago Cubs",
    "away_team": "Athletics",
    "bookmakers": [
      {
        "key": "draftkings",
        "title": "DraftKings",
        "last_update": "2026-06-04T21:05:29.096Z",
        "markets": [
          {
            "key": "h2h",
            "last_update": "2026-06-04T21:05:29.096Z",
            "outcomes": [
              {
                "name": "Chicago Cubs",
                "price": 1.67
              },
              {
                "name": "Athletics",
                "price": 2.23
              }
            ]
          },
          {
            "key": "spreads",
            "last_update": "2026-06-04T21:03:56.713Z",
            "outcomes": [
              {
                "name": "Chicago Cubs",
                "price": 2.44,
                "point": -1.5
              },
              {
                "name": "Athletics",
                "price": 1.57,
                "point": 1.5
              }
            ]
          },
          {
            "key": "totals",
            "last_update": "2026-06-04T20:50:10.783Z",
            "outcomes": [
              {
                "name": "Over",
                "price": 1.86,
                "point": 10.0
              },
              {
                "name": "Under",
                "price": 1.96,
                "point": 10.0
              }
            ]
          }
        ]
      }
    ]
  },
  {
    "id": "63303705",
    "sport_key": "baseball_mlb",
    "sport_title": "MLB",
    "commence_time": "2026-06-05T01:40:00Z",
    "home_team": "Arizona Diamondbacks",
    "away_team": "Los Angeles Dodgers",
    "bookmakers": [
      {
        "key": "draftkings",
        "title": "DraftKings",
        "last_update": "2026-06-04T21:42:38.257Z",
        "markets": [
          {
            "key": "h2h",
            "last_update": "2026-06-04T21:42:38.257Z",
            "outcomes": [
              {
                "name": "Arizona Diamondbacks",
                "price": 2.14
              },
              {
                "name": "Los Angeles Dodgers",
                "price": 1.72
              }
            ]
          },
          {
            "key": "spreads",
            "last_update": "2026-06-04T21:42:07.404Z",
            "outcomes": [
              {
                "name": "Arizona Diamondbacks",
                "price": 1.7,
                "point": 1.5
              },
              {
                "name": "Los Angeles Dodgers",
                "price": 2.18,
                "point": -1.5
              }
            ]
          },
          {
            "key": "totals",
            "last_update": "2026-06-04T17:05:28.697Z",
            "outcomes": [
              {
                "name": "Over",
                "price": 1.93,
                "point": 9.0
              },
              {
                "name": "Under",
                "price": 1.89,
                "point": 9.0
              }
            ]
          }
        ]
      }
    ]
  },
  {
    "id": "63299231",
    "sport_key": "baseball_mlb",
    "sport_title": "MLB",
    "commence_time": "2026-06-05T22:40:00Z",
    "home_team": "Detroit Tigers",
    "away_team": "Seattle Mariners",
    "bookmakers": [
      {
        "key": "draftkings",
        "title": "DraftKings",
        "last_update": "2026-06-04T21:37:56.532Z",
        "markets": [
          {
            "key": "h2h",
            "last_update": "2026-06-04T21:37:56.532Z",
            "outcomes": [
              {
                "name": "Detroit Tigers",
                "price": 2.09
              },
              {
                "name": "Seattle Mariners",
                "price": 1.76
              }
            ]
          },
          {
            "key": "spreads",
            "last_update": "2026-06-04T21:37:56.532Z",
            "outcomes": [
              {
                "name": "Detroit Tigers",
                "price": 1.64,
                "point": 1.5
              },
              {
                "name": "Seattle Mariners",
                "price": 2.29,
                "point": -1.5
              }
            ]
          },
          {
            "key": "totals",
            "last_update": "2026-06-04T21:37:56.532Z",
            "outcomes": [
              {
                "name": "Over",
                "price": 1.97,
                "point": 8.0
              },
              {
                "name": "Under",
                "price": 1.85,
                "point": 8.0
              }
            ]
          }
        ]
      }
    ]
  },
  {
    "id": "63301389",
    "sport_key": "baseball_mlb",
    "sport_title": "MLB",
    "commence_time": "2026-06-06T00:15:00Z",
    "home_team": "Minnesota Twins",
    "away_team": "Kansas City Royals",
    "bookmakers": [
      {
        "key": "draftkings",
        "title": "DraftKings",
        "last_update": "2026-06-04T21:44:10.526Z",
        "markets": [
          {
            "key": "h2h",
            "last_update": "2026-06-04T21:44:10.526Z",
            "outcomes": [
              {
                "name": "Minnesota Twins",
                "price": 1.86
              },
              {
                "name": "Kansas City Royals",
                "price": 1.95
              }
            ]
          },
          {
            "key": "spreads",
            "last_update": "2026-06-04T21:44:10.526Z",
            "outcomes": [
              {
                "name": "Minnesota Twins",
                "price": 1.51,
                "point": 1.5
              },
              {
                "name": "Kansas City Royals",
                "price": 2.59,
                "point": -1.5
              }
            ]
          },
          {
            "key": "totals",
            "last_update": "2026-06-04T21:44:10.526Z",
            "outcomes": [
              {
                "name": "Over",
                "price": 1.92,
                "point": 8.5
              },
              {
                "name": "Under",
                "price": 1.89,
                "point": 8.5
              }
            ]
          }
        ]
      }
    ]
  },
  {
    "id": "63301039",
    "sport_key": "baseball_mlb",
    "sport_title": "MLB",
    "commence_time": "2026-06-05T00:10:00Z",
    "home_team": "Houston Astros",
    "away_team": "Pittsburgh Pirates",
    "bookmakers": [
      {
        "key": "draftkings",
        "title": "DraftKings",
        "last_update": "2026-06-04T21:44:56.551Z",
        "markets": [
          {
            "key": "h2h",
            "last_update": "2026-06-04T16:22:47.285Z",
            "outcomes": [
              {
                "name": "Houston Astros",
                "price": 1.87
              },
              {
                "name": "Pittsburgh Pirates",
                "price": 1.95
              }
            ]
          },
          {
            "key": "spreads",
            "last_update": "2026-06-04T21:44:56.551Z",
            "outcomes": [
              {
                "name": "Houston Astros",
                "price": 1.53,
                "point": 1.5
              },
              {
                "name": "Pittsburgh Pirates",
                "price": 2.53,
                "point": -1.5
              }
            ]
          },
          {
            "key": "totals",
            "last_update": "2026-06-04T16:57:46.061Z",
            "outcomes": [
              {
                "name": "Over",
                "price": 1.94,
                "point": 8.5
              },
              {
                "name": "Under",
                "price": 1.88,
                "point": 8.5
              }
            ]
          }
        ]
      }
    ]
  },
  {
    "id": "63301997",
    "sport_key": "baseball_mlb",
    "sport_title": "MLB",
    "commence_time": "2026-06-05T22:40:00Z",
    "home_team": "Philadelphia Phillies",
    "away_team": "Chicago White Sox",
    "bookmakers": [
      {
        "key": "draftkings",
        "title": "DraftKings",
        "last_update": "2026-06-04T21:38:12.563Z",
        "markets": [
          {
            "key": "h2h",
            "last_update": "2026-06-04T21:38:12.563Z",
            "outcomes": [
              {
                "name": "Philadelphia Phillies",
                "price": 1.53
              },
              {
                "name": "Chicago White Sox",
                "price": 2.53
              }
            ]
          },
          {
            "key": "spreads",
            "last_update": "2026-06-04T21:38:12.563Z",
            "outcomes": [
              {
                "name": "Philadelphia Phillies",
                "price": 2.09,
                "point": -1.5
              },
              {
                "name": "Chicago White Sox",
                "price": 1.76,
                "point": 1.5
              }
            ]
          },
          {
            "key": "totals",
            "last_update": "2026-06-04T21:38:12.563Z",
            "outcomes": [
              {
                "name": "Over",
                "price": 1.89,
                "point": 8.5
              },
              {
                "name": "Under",
                "price": 1.92,
                "point": 8.5
              }
            ]
          }
        ]
      }
    ]
  },
  {
    "id": "63303331",
    "sport_key": "baseball_mlb",
    "sport_title": "MLB",
    "commence_time": "2026-06-05T23:10:00Z",
    "home_team": "Miami Marlins",
    "away_team": "Tampa Bay Rays",
    "bookmakers": [
      {
        "key": "draftkings",
        "title": "DraftKings",
        "last_update": "2026-06-04T21:44:10.526Z",
        "markets": [
          {
            "key": "h2h",
            "last_update": "2026-06-04T21:38:28.205Z",
            "outcomes": [
              {
                "name": "Miami Marlins",
                "price": 2.19
              },
              {
                "name": "Tampa Bay Rays",
                "price": 1.69
              }
            ]
          },
          {
            "key": "spreads",
            "last_update": "2026-06-04T21:44:10.526Z",
            "outcomes": [
              {
                "name": "Miami Marlins",
                "price": 1.73,
                "point": 1.5
              },
              {
                "name": "Tampa Bay Rays",
                "price": 2.13,
                "point": -1.5
              }
            ]
          },
          {
            "key": "totals",
            "last_update": "2026-06-04T21:38:28.205Z",
            "outcomes": [
              {
                "name": "Over",
                "price": 1.89,
                "point": 7.5
              },
              {
                "name": "Under",
                "price": 1.92,
                "point": 7.5
              }
            ]
          }
        ]
      }
    ]
  },
  {
    "id": "63299195",
    "sport_key": "baseball_mlb",
    "sport_title": "MLB",
    "commence_time": "2026-06-06T00:15:00Z",
    "home_team": "Texas Rangers",
    "away_team": "Cleveland Guardians",
    "bookmakers": [
      {
        "key": "draftkings",
        "title": "DraftKings",
        "last_update": "2026-06-04T21:44:10.526Z",
        "markets": [
          {
            "key": "h2h",
            "last_update": "2026-06-04T21:44:10.526Z",
            "outcomes": [
              {
                "name": "Texas Rangers",
                "price": 2.19
              },
              {
                "name": "Cleveland Guardians",
                "price": 1.69
              }
            ]
          },
          {
            "key": "spreads",
            "last_update": "2026-06-04T21:44:10.526Z",
            "outcomes": [
              {
                "name": "Texas Rangers",
                "price": 1.69,
                "point": 1.5
              },
              {
                "name": "Cleveland Guardians",
                "price": 2.19,
                "point": -1.5
              }
            ]
          },
          {
            "key": "totals",
            "last_update": "2026-06-04T21:44:10.526Z",
            "outcomes": [
              {
                "name": "Over",
                "price": 2.04,
                "point": 7.5
              },
              {
                "name": "Under",
                "price": 1.8,
                "point": 7.5
              }
            ]
          }
        ]
      }
    ]
  },
  {
    "id": "63299451",
    "sport_key": "baseball_mlb",
    "sport_title": "MLB",
    "commence_time": "2026-06-04T23:15:00Z",
    "home_team": "Atlanta Braves",
    "away_team": "Toronto Blue Jays",
    "bookmakers": [
      {
        "key": "draftkings",
        "title": "DraftKings",
        "last_update": "2026-06-04T20:13:58.357Z",
        "markets": [
          {
            "key": "h2h",
            "last_update": "2026-06-04T19:57:45.213Z",
            "outcomes": [
              {
                "name": "Atlanta Braves",
                "price": 1.38
              },
              {
                "name": "Toronto Blue Jays",
                "price": 3.1
              }
            ]
          },
          {
            "key": "spreads",
            "last_update": "2026-06-04T19:57:45.213Z",
            "outcomes": [
              {
                "name": "Atlanta Braves",
                "price": 1.88,
                "point": -1.5
              },
              {
                "name": "Toronto Blue Jays",
                "price": 1.93,
                "point": 1.5
              }
            ]
          },
          {
            "key": "totals",
            "last_update": "2026-06-04T20:13:58.357Z",
            "outcomes": [
              {
                "name": "Over",
                "price": 1.93,
                "point": 7.5
              },
              {
                "name": "Under",
                "price": 1.88,
                "point": 7.5
              }
            ]
          }
        ]
      }
    ]
  },
  {
    "id": "63303517",
    "sport_key": "baseball_mlb",
    "sport_title": "MLB",
    "commence_time": "2026-06-04T23:40:00Z",
    "home_team": "Minnesota Twins",
    "away_team": "Kansas City Royals",
    "bookmakers": [
      {
        "key": "draftkings",
        "title": "DraftKings",
        "last_update": "2026-06-04T21:30:34.303Z",
        "markets": [
          {
            "key": "h2h",
            "last_update": "2026-06-04T21:30:34.303Z",
            "outcomes": [
              {
                "name": "Minnesota Twins",
                "price": 1.97
              },
              {
                "name": "Kansas City Royals",
                "price": 1.85
              }
            ]
          },
          {
            "key": "spreads",
            "last_update": "2026-06-04T21:26:46.203Z",
            "outcomes": [
              {
                "name": "Minnesota Twins",
                "price": 1.61,
                "point": 1.5
              },
              {
                "name": "Kansas City Royals",
                "price": 2.35,
                "point": -1.5
              }
            ]
          },
          {
            "key": "totals",
            "last_update": "2026-06-04T21:30:34.303Z",
            "outcomes": [
              {
                "name": "Over",
                "price": 1.83,
                "point": 9.0
              },
              {
                "name": "Under",
                "price": 2.0,
                "point": 9.0
              }
            ]
          }
        ]
      }
    ]
  },
  {
    "id": "63302623",
    "sport_key": "baseball_mlb",
    "sport_title": "MLB",
    "commence_time": "2026-06-06T00:15:00Z",
    "home_team": "St. Louis Cardinals",
    "away_team": "Cincinnati Reds",
    "bookmakers": [
      {
        "key": "draftkings",
        "title": "DraftKings",
        "last_update": "2026-06-04T21:44:10.526Z",
        "markets": [
          {
            "key": "h2h",
            "last_update": "2026-06-04T21:44:10.526Z",
            "outcomes": [
              {
                "name": "St. Louis Cardinals",
                "price": 1.73
              },
              {
                "name": "Cincinnati Reds",
                "price": 2.13
              }
            ]
          },
          {
            "key": "spreads",
            "last_update": "2026-06-04T21:44:10.526Z",
            "outcomes": [
              {
                "name": "St. Louis Cardinals",
                "price": 2.53,
                "point": -1.5
              },
              {
                "name": "Cincinnati Reds",
                "price": 1.53,
                "point": 1.5
              }
            ]
          },
          {
            "key": "totals",
            "last_update": "2026-06-04T21:44:10.526Z",
            "outcomes": [
              {
                "name": "Over",
                "price": 1.83,
                "point": 9.0
              },
              {
                "name": "Under",
                "price": 2.0,
                "point": 9.0
              }
            ]
          }
        ]
      }
    ]
  },
  {
    "id": "63300949",
    "sport_key": "baseball_mlb",
    "sport_title": "MLB",
    "commence_time": "2026-06-06T00:40:00Z",
    "home_team": "Colorado Rockies",
    "away_team": "Milwaukee Brewers",
    "bookmakers": [
      {
        "key": "draftkings",
        "title": "DraftKings",
        "last_update": "2026-06-04T21:44:25.874Z",
        "markets": [
          {
            "key": "h2h",
            "last_update": "2026-06-04T21:44:25.874Z",
            "outcomes": [
              {
                "name": "Colorado Rockies",
                "price": 2.29
              },
              {
                "name": "Milwaukee Brewers",
                "price": 1.64
              }
            ]
          },
          {
            "key": "spreads",
            "last_update": "2026-06-04T21:44:25.874Z",
            "outcomes": [
              {
                "name": "Colorado Rockies",
                "price": 1.81,
                "point": 1.5
              },
              {
                "name": "Milwaukee Brewers",
                "price": 2.02,
                "point": -1.5
              }
            ]
          },
          {
            "key": "totals",
            "last_update": "2026-06-04T21:44:25.874Z",
            "outcomes": [
              {
                "name": "Over",
                "price": 1.88,
                "point": 11.5
              },
              {
                "name": "Under",
                "price": 1.93,
                "point": 11.5
              }
            ]
          }
        ]
      }
    ]
  },
  {
    "id": "63302201",
    "sport_key": "baseball_mlb",
    "sport_title": "MLB",
    "commence_time": "2026-06-06T01:40:00Z",
    "home_team": "San Diego Padres",
    "away_team": "New York Mets",
    "bookmakers": [
      {
        "key": "draftkings",
        "title": "DraftKings",
        "last_update": "2026-06-04T21:44:41.407Z",
        "markets": [
          {
            "key": "h2h",
            "last_update": "2026-06-04T21:44:41.407Z",
            "outcomes": [
              {
                "name": "San Diego Padres",
                "price": 1.76
              },
              {
                "name": "New York Mets",
                "price": 2.09
              }
            ]
          },
          {
            "key": "spreads",
            "last_update": "2026-06-04T21:44:41.407Z",
            "outcomes": [
              {
                "name": "San Diego Padres",
                "price": 2.69,
                "point": -1.5
              },
              {
                "name": "New York Mets",
                "price": 1.48,
                "point": 1.5
              }
            ]
          },
          {
            "key": "totals",
            "last_update": "2026-06-04T21:44:41.407Z",
            "outcomes": [
              {
                "name": "Over",
                "price": 1.8,
                "point": 7.0
              },
              {
                "name": "Under",
                "price": 2.04,
                "point": 7.0
              }
            ]
          }
        ]
      }
    ]
  },
  {
    "id": "63303813",
    "sport_key": "baseball_mlb",
    "sport_title": "MLB",
    "commence_time": "2026-06-06T01:40:00Z",
    "home_team": "Arizona Diamondbacks",
    "away_team": "Washington Nationals",
    "bookmakers": [
      {
        "key": "draftkings",
        "title": "DraftKings",
        "last_update": "2026-06-04T21:44:25.874Z",
        "markets": [
          {
            "key": "h2h",
            "last_update": "2026-06-04T21:44:25.874Z",
            "outcomes": [
              {
                "name": "Arizona Diamondbacks",
                "price": 1.73
              },
              {
                "name": "Washington Nationals",
                "price": 2.13
              }
            ]
          },
          {
            "key": "spreads",
            "last_update": "2026-06-04T21:44:25.874Z",
            "outcomes": [
              {
                "name": "Arizona Diamondbacks",
                "price": 2.53,
                "point": -1.5
              },
              {
                "name": "Washington Nationals",
                "price": 1.53,
                "point": 1.5
              }
            ]
          },
          {
            "key": "totals",
            "last_update": "2026-06-04T21:44:25.874Z",
            "outcomes": [
              {
                "name": "Over",
                "price": 1.95,
                "point": 9.0
              },
              {
                "name": "Under",
                "price": 1.86,
                "point": 9.0
              }
            ]
          }
        ]
      }
    ]
  }
]