[
  {
    "id": "88e10294c54deffd6e9e6efcba249d2c",
    "sport_key": "basketball_nba",
    "sport_title": "NBA",
    "commence_time": "2026-05-01T23:10:00Z",
    "home_team": "Orlando Magic",
    "away_team": "Detroit Pistons",
    "bookmakers": [
      {
        "key": "draftkings",
        "title": "DraftKings",
        "last_update": "2026-05-01T10:53:27Z",
        "markets": [
          {
            "key": "h2h",
            "last_update": "2026-05-01T10:53:27Z",
            "outcomes": [
              {
                "name": "Detroit Pistons",
                "price": 1.62
              },
              {
                "name": "Orlando Magic",
                "price": 2.36
              }
            ]
          },
          {
            "key": "spreads",
            "last_update": "2026-05-01T10:53:27Z",
            "outcomes": [
              {
                "name": "Detroit Pistons",
                "price": 1.91,
                "point": -3.5
              },
              {
                "name": "Orlando Magic",
                "price": 1.91,
                "point": 3.5
              }
            ]
          },
          {
            "key": "totals",
            "last_update": "2026-05-01T10:53:27Z",
            "outcomes": [
              {
                "name": "Over",
                "price": 1.91,
                "point": 209.5
              },
              {
                "name": "Under",
                "price": 1.91,
                "point": 209.5
              }
            ]
          }
        ]
      }
    ]
  },
  {
    "id": "d1938a9c13602a661e894f996f2680e8",
    "sport_key": "basketball_nba",
    "sport_title": "NBA",
    "commence_time": "2026-05-01T23:40:00Z",
    "home_team": "Toronto Raptors",
    "away_team": "Cleveland Cavaliers",
    "bookmakers": [
      {
        "key": "draftkings",
        "title": "DraftKings",
        "last_update": "2026-05-01T10:53:27Z",
        "markets": [
          {
            "key": "h2h",
            "last_update": "2026-05-01T10:53:27Z",
            "outcomes": [
              {
                "name": "Cleveland Cavaliers",
                "price": 1.57
              },
              {
                "name": "Toronto Raptors",
                "price": 2.45
              }
            ]
          },
          {
            "key": "spreads",
            "last_update": "2026-05-01T10:53:27Z",
            "outcomes": [
              {
                "name": "Cleveland Cavaliers",
                "price": 1.87,
                "point": -3.5
              },
              {
                "name": "Toronto Raptors",
                "price": 1.95,
                "point": 3.5
              }
            ]
          },
          {
            "key": "totals",
            "last_update": "2026-05-01T10:53:27Z",
            "outcomes": [
              {
                "name": "Over",
                "price": 1.89,
                "point": 218.5
              },
              {
                "name": "Under",
                "price": 1.93,
                "point": 218.5
              }
            ]
          }
        ]
      }
    ]
  },
  {
    "id": "c361a0b8c035a055bd9497b52674e3fb",
    "sport_key": "basketball_nba",
    "sport_title": "NBA",
    "commence_time": "2026-05-02T01:40:00Z",
    "home_team": "Houston Rockets",
    "away_team": "Los Angeles Lakers",
    "bookmakers": [
      {
        "key": "draftkings",
        "title": "DraftKings",
        "last_update": "2026-05-01T10:53:27Z",
        "markets": [
          {
            "key": "h2h",
            "last_update": "2026-05-01T10:53:27Z",
            "outcomes": [
              {
                "name": "Houston Rockets",
                "price": 1.59
              },
              {
                "name": "Los Angeles Lakers",
                "price": 2.42
              }
            ]
          },
          {
            "key": "spreads",
            "last_update": "2026-05-01T10:53:27Z",
            "outcomes": [
              {
                "name": "Houston Rockets",
                "price": 1.89,
                "point": -3.5
              },
              {
                "name": "Los Angeles Lakers",
                "price": 1.93,
                "point": 3.5
              }
            ]
          },
          {
            "key": "totals",
            "last_update": "2026-05-01T10:53:27Z",
            "outcomes": [
              {
                "name": "Over",
                "price": 1.91,
                "point": 206.5
              },
              {
                "name": "Under",
                "price": 1.91,
                "point": 206.5
              }
            ]
          }
        ]
      }
    ]
  },
  {
    "id": "a37e80a2e3cf3aaa3ae84a9124987058",
    "sport_key": "basketball_nba",
    "sport_title": "NBA",
    "commence_time": "2026-05-02T23:40:00Z",
    "home_team": "Boston Celtics",
    "away_team": "Philadelphia 76ers",
    "bookmakers": [
      {
        "key": "draftkings",
        "title": "DraftKings",
        "last_update": "2026-05-01T10:53:27Z",
        "markets": [
          {
            "key": "h2h",
            "last_update": "2026-05-01T10:53:27Z",
            "outcomes": [
              {
                "name": "Boston Celtics",
                "price": 1.32
              },
              {
                "name": "Philadelphia 76ers",
                "price": 3.5
              }
            ]
          },
          {
            "key": "spreads",
            "last_update": "2026-05-01T10:53:27Z",
            "outcomes": [
              {
                "name": "Boston Celtics",
                "price": 1.95,
                "point": -8.5
              },
              {
                "name": "Philadelphia 76ers",
                "price": 1.87,
                "point": 8.5
              }
            ]
          },
          {
            "key": "totals",
            "last_update": "2026-05-01T10:53:27Z",
            "outcomes": [
              {
                "name": "Over",
                "price": 1.91,
                "point": 206.5
              },
              {
                "name": "Under",
                "price": 1.91,
                "point": 206.5
              }
            ]
          }
        ]
      }
    ]
  },
  {
    "id": "219920e3a715ceb3dc69f3638f7571d5",
    "sport_key": "basketball_nba",
    "sport_title": "NBA",
    "commence_time": "2026-05-05T01:30:00Z",
    "home_team": "San Antonio Spurs",
    "away_team": "Minnesota Timberwolves",
    "bookmakers": [
      {
        "key": "draftkings",
        "title": "DraftKings",
        "last_update": "2026-05-01T10:53:27Z",
        "markets": [
          {
            "key": "h2h",
            "last_update": "2026-05-01T10:53:27Z",
            "outcomes": [
              {
                "name": "Minnesota Timberwolves",
                "price": 7.25
              },
              {
                "name": "San Antonio Spurs",
                "price": 1.11
              }
            ]
          },
          {
            "key": "spreads",
            "last_update": "2026-05-01T10:53:27Z",
            "outcomes": [
              {
                "name": "Minnesota Timberwolves",
                "price": 1.91,
                "point": 14.5
              },
              {
                "name": "San Antonio Spurs",
                "price": 1.91,
                "point": -14.5
              }
            ]
          },
          {
            "key": "totals",
            "last_update": "2026-05-01T10:53:27Z",
            "outcomes": [
              {
                "name": "Over",
                "price": 1.91,
                "point": 217.5
              },
              {
                "name": "Under",
                "price": 1.91,
                "point": 217.5
              }
            ]
          }
        ]
      }
    ]
  }
]